Workbook

Sheet Tarifs 2027
A1: Tarifs hors plateforme
A3: Hors taxes de séjour, draps
A6: Dimanche | B6: Dimanche | D6: Tarifs bruts 2025/26 | E6: Ménage fin de séjour (1) | F6: Frais de gestion | H6: Total client 2025/26 | J6: Tarifs 2026/27 | L6: Réservations | M6: Vacances | N6: Numéro de contrat | O6: Contrat signé | P6: Numéro facture acompte | Q6: Acompte | R6: Paiement acompte | S6: Assurance
A7: 46369 | B7: 46376 | D7: =+'[1]2026'!D5 -> 2590 | E7: 201 | F7: 50 | H7: =+F7+E7+D7 -> 2841 | J7: 3090 | L7: Pour nous | M7: UK
A8: 46376 | B8: 46383 | D8: =+'[1]2026'!D6 -> 4490 | E8: 201 | F8: 50 | H8: =+F8+E8+D8 -> 4741 | J8: 5390 | L8: Famille Laffaure | M8: UK, France | N8: 01 | O8: OK | P8: 01 | Q8: 1617 | R8: OK
A9: 46383 | B9: 46390 | D9: =+'[1]2026'!D7 -> 4690 | E9: 201 | F9: 50 | H9: =+F9+E9+D9 -> 4941 | J9: 5690 | L9: Famille Grellet | M9: UK, France | N9: 02 | O9: OK | P9: 02 | Q9: 1707 | R9: OK
A10: 46390 | B10: 46397 | D10: =+'[1]2026'!D8 -> 2790 | E10: 201 | F10: 50 | H10: =+F10+E10+D10 -> 3041 | J10: 3090 | L10: Michaël Truijen | N10: 03 | O10: OK | P10: 05 | Q10: 1914 | R10: OK | S10: OK
A11: 46397 | B11: 46404 | D11: =+'[1]2026'!D9 -> 2990 | E11: 201 | F11: 50 | H11: =+F11+E11+D11 -> 3241 | J11: 3290 | L11: Michaël Truijen
A12: 46404 | B12: 46411 | D12: =+'[1]2026'!D10 -> 3290 | E12: 201 | F12: 50 | H12: =+F12+E12+D12 -> 3541 | J12: 3650
A13: 46411 | B13: 46418 | D13: =+'[1]2026'!D11 -> 3490 | E13: 201 | F13: 50 | H13: =+F13+E13+D13 -> 3741 | J13: 3850 | L13: Famille Panuel | N13: 04 | O13: OK | P13: 03 | Q13: 1155 | R13: OK | S13: OK
A14: 46418 | B14: 46425 | D14: =+'[1]2026'!D12 -> 3490 | E14: 201 | F14: 50 | H14: =+F14+E14+D14 -> 3741 | J14: 3990
A15: 46425 | B15: 46432 | D15: =+'[1]2026'!D13 -> 4490 | E15: 201 | F15: 50 | H15: =+F15+E15+D15 -> 4741 | J15: 5690 | M15: France Paris
A16: 46432 | B16: 46439 | D16: =+'[1]2026'!D14 -> 4690 | E16: 201 | F16: 50 | H16: =+F16+E16+D16 -> 4941 | J16: 5690 | M16: UK, France Paris
A17: 46439 | B17: 46446 | D17: =+'[1]2026'!D15 -> 4690 | E17: 201 | F17: 50 | H17: =+F17+E17+D17 -> 4941 | J17: 5690 | M17: France
A18: 46446 | B18: 46453 | D18: =+'[1]2026'!D16 -> 4690 | E18: 201 | F18: 50 | H18: =+F18+E18+D18 -> 4941 | J18: 5690 | M18: France
A19: 46453 | B19: 46460 | D19: =+'[1]2026'!D17 -> 3490 | E19: 201 | F19: 50 | H19: =+F19+E19+D19 -> 3741 | J19: 3890
A20: 46460 | B20: 46467 | D20: =+'[1]2026'!D18 -> 2990 | E20: 201 | F20: 50 | H20: =+F20+E20+D20 -> 3241 | J20: 3390
A21: 46467 | B21: 46474 | D21: =+'[1]2026'!D19 -> 2590 | E21: 201 | F21: 50 | H21: =+F21+E21+D21 -> 2841 | J21: 2990 | L21: Milon | N21: 05 | O21: OK | P21: 04 | Q21: 897 | R21: OK
A22: 46474 | B22: 46481 | D22: =+'[1]2026'!D20 -> 2590 | E22: 201 | F22: 50 | H22: =+F22+E22+D22 -> 2841 | J22: 3390 | L22: Cunningham Jack | M22: UK | N22: 06 | P22: 06 | Q22: 1017 | R22: OK
A23: 46481 | B23: 46488 | D23: =+'[1]2026'!D21 -> 2990 | E23: 201 | F23: 50 | H23: =+F23+E23+D23 -> 3241 | J23: 3390 | M23: UK, France
A24: 46488 | B24: 46495 | D24: =+'[1]2026'!D22 -> 2290 | E24: 201 | F24: 50 | H24: =+F24+E24+D24 -> 2541 | J24: 2690 | M24: UK, France
A25: 46495 | B25: 46502 | D25: =+'[1]2026'!D23 -> 1990 | E25: 201 | F25: 50 | H25: =+F25+E25+D25 -> 2241 | J25: 2390 | M25: France
B27: Total | D27: =+SUM(D7:D26) -> 65310 | E27: =+SUM(E7:E26) -> 3819 | F27: =+SUM(F7:F26) -> 950 | H27: =+SUM(H7:H26) -> 70079 | J27: =+SUM(J7:J26) -> 76930
A29: (1) : Seuls 3 clients n'ont pas pris le ménage en 2025/26

Sheet Prop tarifs Alp Agence
C2: Proposition 2026/27 Alp Agence | D2: Tarifs 2025/26 | E2: Variation | G2: Vacances 2026/27 | I2: Proposition 2026/27 Loc directe
A3: 46368 | B3: 46375 | C3: 3090 | D3: =+'[1]2026'!D5 -> 2590 | E3: =+(C3-D3)/D3 -> 0.19305019 | G3: UK | I3: =+'Simulations hors agence'!M11 -> 3090
A4: 46375 | B4: 46382 | C4: 5690 | D4: =+'[1]2026'!D6 -> 4490 | E4: =+(C4-D4)/D4 -> 0.26726058 | G4: UK, France | I4: =+'Simulations hors agence'!M12 -> 5390
A5: 46382 | B5: 46389 | C5: 5690 | D5: =+'[1]2026'!D7 -> 4690 | E5: =+(C5-D5)/D5 -> 0.21321962 | G5: UK, France | I5: =+'Simulations hors agence'!M13 -> 5690
A6: 46389 | B6: 46396 | C6: 3190 | D6: =+'[1]2026'!D8 -> 2790 | E6: =+(C6-D6)/D6 -> 0.14336918 | I6: =+'Simulations hors agence'!M14 -> 3090
A7: 46396 | B7: 46403 | C7: 3290 | D7: =+'[1]2026'!D9 -> 2990 | E7: =+(C7-D7)/D7 -> 0.10033445 | I7: =+'Simulations hors agence'!M15 -> 3290
A8: 46403 | B8: 46410 | C8: 3490 | D8: =+'[1]2026'!D10 -> 3290 | E8: =+(C8-D8)/D8 -> 0.060790274 | I8: =+'Simulations hors agence'!M16 -> 3650
A9: 46410 | B9: 46417 | C9: 3790 | D9: =+'[1]2026'!D11 -> 3490 | E9: =+(C9-D9)/D9 -> 0.085959885 | I9: =+'Simulations hors agence'!M17 -> 3850
A10: 46417 | B10: 46424 | C10: 3990 | D10: =+'[1]2026'!D12 -> 3490 | E10: =+(C10-D10)/D10 -> 0.14326648 | I10: =+'Simulations hors agence'!M18 -> 3990
A11: 46424 | B11: 46431 | C11: 5690 | D11: =+'[1]2026'!D13 -> 4490 | E11: =+(C11-D11)/D11 -> 0.26726058 | G11: France Paris | I11: =+'Simulations hors agence'!M19 -> 5690
A12: 46431 | B12: 46438 | C12: 5690 | D12: =+'[1]2026'!D14 -> 4690 | E12: =+(C12-D12)/D12 -> 0.21321962 | G12: UK, France Paris | I12: =+'Simulations hors agence'!M20 -> 5690
A13: 46438 | B13: 46445 | C13: 5490 | D13: =+'[1]2026'!D15 -> 4690 | E13: =+(C13-D13)/D13 -> 0.17057569 | G13: France | I13: =+'Simulations hors agence'!M21 -> 5690
A14: 46445 | B14: 46452 | C14: 5490 | D14: =+'[1]2026'!D16 -> 4690 | E14: =+(C14-D14)/D14 -> 0.17057569 | G14: France | I14: =+'Simulations hors agence'!M22 -> 5690
A15: 46452 | B15: 46459 | C15: 3890 | D15: =+'[1]2026'!D17 -> 3490 | E15: =+(C15-D15)/D15 -> 0.11461318 | I15: =+'Simulations hors agence'!M23 -> 3890
A16: 46459 | B16: 46466 | C16: 3490 | D16: =+'[1]2026'!D18 -> 2990 | E16: =+(C16-D16)/D16 -> 0.16722408 | I16: =+'Simulations hors agence'!M24 -> 3390
A17: 46466 | B17: 46473 | C17: 3090 | D17: =+'[1]2026'!D19 -> 2590 | E17: =+(C17-D17)/D17 -> 0.19305019 | I17: =+'Simulations hors agence'!M25 -> 2990
A18: 46473 | B18: 46480 | C18: 3090 | D18: =+'[1]2026'!D20 -> 2590 | E18: =+(C18-D18)/D18 -> 0.19305019 | G18: UK | I18: =+'Simulations hors agence'!M26 -> 3390
A19: 46480 | B19: 46487 | C19: 3290 | D19: =+'[1]2026'!D21 -> 2990 | E19: =+(C19-D19)/D19 -> 0.10033445 | G19: UK, France | I19: =+'Simulations hors agence'!M27 -> 3390
A20: 46487 | B20: 46494 | C20: 2490 | D20: =+'[1]2026'!D22 -> 2290 | E20: =+(C20-D20)/D20 -> 0.087336245 | G20: UK, France | I20: =+'Simulations hors agence'!M28 -> 2690
A21: 46494 | B21: 46501 | C21: 2090 | D21: =+'[1]2026'!D23 -> 1990 | E21: =+(C21-D21)/D21 -> 0.050251256 | G21: France | I21: =+'Simulations hors agence'!M29 -> 2390

Sheet Simulations hors agence
A1: Tarifs hors plateforme
A3: Montant dépenses permettant une réduction d'impôt : 12000€. Pour le foyer fiscal. Ces dépenses ouvrent une réduction de 50%
A4: Dépenses femme de ménage Paris : 600*11=> 6500 euros environ
A7: Hors taxes de séjour, draps
A10: Dimanche | B10: Dimanche | D10: Tarifs 2025/26 | E10: Ménage fin de séjour (6) | F10: Frais de gestion | G10: Partage honoraires (5) | I10: Total client | J10: Part proprio (1) | K10: % proprio | M10: Tarifs 2026/27 | N10: Ménage fin de séjour | O10: Accueil / Départ | P10: Panier accueil | Q10: Presta supp (2) | R10: Gestion paiement (3) | S10: Caution (7) | T10: Assurance proprio (4) | U10: Montée en gamme (8) | W10: Total client | X10: Part proprio (1) | Y10: % proprio | AA10: Variation client € | AB10: Variation proprio € | AD10: Variation client % | AE10: Variation proprio % | AG10: Var. proprio tarifs 2026 € | AH10: Var. proprio tarifs 2026 %
A11: 46369 | B11: 46376 | D11: =+'[1]2026'!D5 -> 2590 | E11: 201 | F11: 50 | G11: 115 | I11: =+F11+E11+D11 -> 2841 | J11: =(D11-198)*0.78+G11 -> 1980.76 | K11: =+J11/I11 -> 0.69720521 | M11: 3090 | N11: 350 | O11: 90 | P11: 50 | Q11: =(90/4) -> 22.5 | R11: =+M11*0.02 -> 61.8 | S11: 20 | T11: 15 | U11: 10 | W11: =+M11 -> 3090 | X11: =+M11-SUM(N11:U11) -> 2470.7 | Y11: =+X11/W11 -> 0.79957929 | AA11: =+W11-I11 -> 249 | AB11: =+X11-J11 -> 489.94 | AD11: =+(W11-I11)/I11 -> 0.087645195 | AE11: =+(X11-J11)/J11 -> 0.2473495 | AG11: =+I11-SUM(N11:U11)-J11 -> 240.94 | AH11: =+(+I11-SUM(N11:U11)-J11)/J11 -> 0.12164018
A12: 46376 | B12: 46383 | D12: =+'[1]2026'!D6 -> 4490 | E12: 201 | F12: 50 | G12: 115 | I12: =+F12+E12+D12 -> 4741 | J12: =(D12-198)*0.78+G12 -> 3462.76 | K12: =+J12/I12 -> 0.73038599 | M12: 5390 | N12: 350 | O12: 90 | P12: 50 | Q12: =(90/4) -> 22.5 | R12: =+M12*0.02 -> 107.8 | S12: 20 | T12: 15 | U12: 10 | W12: =+M12 -> 5390 | X12: =+M12-SUM(N12:U12) -> 4724.7 | Y12: =+X12/W12 -> 0.87656772 | AA12: =+W12-I12 -> 649 | AB12: =+X12-J12 -> 1261.94 | AD12: =+(W12-I12)/I12 -> 0.13689095 | AE12: =+(X12-J12)/J12 -> 0.36443184 | AG12: =+I12-SUM(N12:U12)-J12 -> 612.94 | AH12: =+(+I12-SUM(N12:U12)-J12)/J12 -> 0.17700909
A13: 46383 | B13: 46390 | D13: =+'[1]2026'!D7 -> 4690 | E13: 201 | F13: 50 | G13: 115 | I13: =+F13+E13+D13 -> 4941 | J13: =(D13-198)*0.78+G13 -> 3618.76 | K13: =+J13/I13 -> 0.73239425 | M13: 5690 | N13: 350 | O13: 90 | P13: 50 | Q13: =(90/4) -> 22.5 | R13: =+M13*0.02 -> 113.8 | S13: 20 | T13: 15 | U13: 10 | W13: =+M13 -> 5690 | X13: =+M13-SUM(N13:U13) -> 5018.7 | Y13: =+X13/W13 -> 0.88202109 | AA13: =+W13-I13 -> 749 | AB13: =+X13-J13 -> 1399.94 | AD13: =+(W13-I13)/I13 -> 0.15158875 | AE13: =+(X13-J13)/J13 -> 0.38685627 | AG13: =+I13-SUM(N13:U13)-J13 -> 650.94 | AH13: =+(+I13-SUM(N13:U13)-J13)/J13 -> 0.1798793
A14: 46390 | B14: 46397 | D14: =+'[1]2026'!D8 -> 2790 | E14: 201 | F14: 50 | G14: 115 | I14: =+F14+E14+D14 -> 3041 | J14: =(D14-198)*0.78+G14 -> 2136.76 | K14: =+J14/I14 -> 0.70265044 | M14: 3090 | N14: 350 | O14: 90 | P14: 50 | Q14: =(90/4) -> 22.5 | R14: =+M14*0.02 -> 61.8 | S14: 20 | T14: 15 | U14: 10 | W14: =+M14 -> 3090 | X14: =+M14-SUM(N14:U14) -> 2470.7 | Y14: =+X14/W14 -> 0.79957929 | AA14: =+W14-I14 -> 49 | AB14: =+X14-J14 -> 333.94 | AD14: =+(W14-I14)/I14 -> 0.016113121 | AE14: =+(X14-J14)/J14 -> 0.15628334 | AG14: =+I14-SUM(N14:U14)-J14 -> 284.94 | AH14: =+(+I14-SUM(N14:U14)-J14)/J14 -> 0.13335143
A15: 46397 | B15: 46404 | D15: =+'[1]2026'!D9 -> 2990 | E15: 201 | F15: 50 | G15: 115 | I15: =+F15+E15+D15 -> 3241 | J15: =(D15-198)*0.78+G15 -> 2292.76 | K15: =+J15/I15 -> 0.70742363 | M15: 3290 | N15: 350 | O15: 90 | P15: 50 | Q15: =(90/4) -> 22.5 | R15: =+M15*0.02 -> 65.8 | S15: 20 | T15: 15 | U15: 10 | W15: =+M15 -> 3290 | X15: =+M15-SUM(N15:U15) -> 2666.7 | Y15: =+X15/W15 -> 0.81054711 | AA15: =+W15-I15 -> 49 | AB15: =+X15-J15 -> 373.94 | AD15: =+(W15-I15)/I15 -> 0.01511879 | AE15: =+(X15-J15)/J15 -> 0.16309601 | AG15: =+I15-SUM(N15:U15)-J15 -> 324.94 | AH15: =+(+I15-SUM(N15:U15)-J15)/J15 -> 0.14172438
A16: 46404 | B16: 46411 | D16: =+'[1]2026'!D10 -> 3290 | E16: 201 | F16: 50 | G16: 115 | I16: =+F16+E16+D16 -> 3541 | J16: =(D16-198)*0.78+G16 -> 2526.76 | K16: =+J16/I16 -> 0.71357244 | M16: 3650 | N16: 350 | O16: 90 | P16: 50 | Q16: =(90/4) -> 22.5 | R16: =+M16*0.02 -> 73 | S16: 20 | T16: 15 | U16: 10 | W16: =+M16 -> 3650 | X16: =+M16-SUM(N16:U16) -> 3019.5 | Y16: =+X16/W16 -> 0.82726027 | AA16: =+W16-I16 -> 109 | AB16: =+X16-J16 -> 492.74 | AD16: =+(W16-I16)/I16 -> 0.030782265 | AE16: =+(X16-J16)/J16 -> 0.19500863 | AG16: =+I16-SUM(N16:U16)-J16 -> 383.74 | AH16: =+(+I16-SUM(N16:U16)-J16)/J16 -> 0.15187038
A17: 46411 | B17: 46418 | D17: =+'[1]2026'!D11 -> 3490 | E17: 201 | F17: 50 | G17: 115 | I17: =+F17+E17+D17 -> 3741 | J17: =(D17-198)*0.78+G17 -> 2682.76 | K17: =+J17/I17 -> 0.71712376 | M17: 3850 | N17: 350 | O17: 90 | P17: 50 | Q17: =(90/4) -> 22.5 | R17: =+M17*0.02 -> 77 | S17: 20 | T17: 15 | U17: 10 | W17: =+M17 -> 3850 | X17: =+M17-SUM(N17:U17) -> 3215.5 | Y17: =+X17/W17 -> 0.83519481 | AA17: =+W17-I17 -> 109 | AB17: =+X17-J17 -> 532.74 | AD17: =+(W17-I17)/I17 -> 0.029136594 | AE17: =+(X17-J17)/J17 -> 0.19857908 | AG17: =+I17-SUM(N17:U17)-J17 -> 423.74 | AH17: =+(+I17-SUM(N17:U17)-J17)/J17 -> 0.15794928
A18: 46418 | B18: 46425 | D18: =+'[1]2026'!D12 -> 3490 | E18: 201 | F18: 50 | G18: 115 | I18: =+F18+E18+D18 -> 3741 | J18: =(D18-198)*0.78+G18 -> 2682.76 | K18: =+J18/I18 -> 0.71712376 | M18: 3990 | N18: 350 | O18: 90 | P18: 50 | Q18: =(90/4) -> 22.5 | R18: =+M18*0.02 -> 79.8 | S18: 20 | T18: 15 | U18: 10 | W18: =+M18 -> 3990 | X18: =+M18-SUM(N18:U18) -> 3352.7 | Y18: =+X18/W18 -> 0.84027569 | AA18: =+W18-I18 -> 249 | AB18: =+X18-J18 -> 669.94 | AD18: =+(W18-I18)/I18 -> 0.066559743 | AE18: =+(X18-J18)/J18 -> 0.24972044 | AG18: =+I18-SUM(N18:U18)-J18 -> 420.94 | AH18: =+(+I18-SUM(N18:U18)-J18)/J18 -> 0.15690557
A19: 46425 | B19: 46432 | D19: =+'[1]2026'!D13 -> 4490 | E19: 201 | F19: 50 | G19: 115 | I19: =+F19+E19+D19 -> 4741 | J19: =(D19-198)*0.78+G19 -> 3462.76 | K19: =+J19/I19 -> 0.73038599 | M19: 5690 | N19: 350 | O19: 90 | P19: 50 | Q19: =(90/4) -> 22.5 | R19: =+M19*0.02 -> 113.8 | S19: 20 | T19: 15 | U19: 10 | W19: =+M19 -> 5690 | X19: =+M19-SUM(N19:U19) -> 5018.7 | Y19: =+X19/W19 -> 0.88202109 | AA19: =+W19-I19 -> 949 | AB19: =+X19-J19 -> 1555.94 | AD19: =+(W19-I19)/I19 -> 0.20016874 | AE19: =+(X19-J19)/J19 -> 0.44933521 | AG19: =+I19-SUM(N19:U19)-J19 -> 606.94 | AH19: =+(+I19-SUM(N19:U19)-J19)/J19 -> 0.17527637
A20: 46432 | B20: 46439 | D20: =+'[1]2026'!D14 -> 4690 | E20: 201 | F20: 50 | G20: 115 | I20: =+F20+E20+D20 -> 4941 | J20: =(D20-198)*0.78+G20 -> 3618.76 | K20: =+J20/I20 -> 0.73239425 | M20: 5690 | N20: 350 | O20: 90 | P20: 50 | Q20: =(90/4) -> 22.5 | R20: =+M20*0.02 -> 113.8 | S20: 20 | T20: 15 | U20: 10 | W20: =+M20 -> 5690 | X20: =+M20-SUM(N20:U20) -> 5018.7 | Y20: =+X20/W20 -> 0.88202109 | AA20: =+W20-I20 -> 749 | AB20: =+X20-J20 -> 1399.94 | AD20: =+(W20-I20)/I20 -> 0.15158875 | AE20: =+(X20-J20)/J20 -> 0.38685627 | AG20: =+I20-SUM(N20:U20)-J20 -> 650.94 | AH20: =+(+I20-SUM(N20:U20)-J20)/J20 -> 0.1798793
A21: 46439 | B21: 46446 | D21: =+'[1]2026'!D15 -> 4690 | E21: 201 | F21: 50 | G21: 115 | I21: =+F21+E21+D21 -> 4941 | J21: =(D21-198)*0.78+G21 -> 3618.76 | K21: =+J21/I21 -> 0.73239425 | M21: 5690 | N21: 350 | O21: 90 | P21: 50 | Q21: =(90/4) -> 22.5 | R21: =+M21*0.02 -> 113.8 | S21: 20 | T21: 15 | U21: 10 | W21: =+M21 -> 5690 | X21: =+M21-SUM(N21:U21) -> 5018.7 | Y21: =+X21/W21 -> 0.88202109 | AA21: =+W21-I21 -> 749 | AB21: =+X21-J21 -> 1399.94 | AD21: =+(W21-I21)/I21 -> 0.15158875 | AE21: =+(X21-J21)/J21 -> 0.38685627 | AG21: =+I21-SUM(N21:U21)-J21 -> 650.94 | AH21: =+(+I21-SUM(N21:U21)-J21)/J21 -> 0.1798793
A22: 46446 | B22: 46453 | D22: =+'[1]2026'!D16 -> 4690 | E22: 201 | F22: 50 | G22: 115 | I22: =+F22+E22+D22 -> 4941 | J22: =(D22-198)*0.78+G22 -> 3618.76 | K22: =+J22/I22 -> 0.73239425 | M22: 5690 | N22: 350 | O22: 90 | P22: 50 | Q22: =(90/4) -> 22.5 | R22: =+M22*0.02 -> 113.8 | S22: 20 | T22: 15 | U22: 10 | W22: =+M22 -> 5690 | X22: =+M22-SUM(N22:U22) -> 5018.7 | Y22: =+X22/W22 -> 0.88202109 | AA22: =+W22-I22 -> 749 | AB22: =+X22-J22 -> 1399.94 | AD22: =+(W22-I22)/I22 -> 0.15158875 | AE22: =+(X22-J22)/J22 -> 0.38685627 | AG22: =+I22-SUM(N22:U22)-J22 -> 650.94 | AH22: =+(+I22-SUM(N22:U22)-J22)/J22 -> 0.1798793
... A29: 46495 | B29: 46502 | D29: =+'[1]2026'!D23 -> 1990 | E29: 201 | F29: 50 | G29: 115 | I29: =+F29+E29+D29 -> 2241 | J29: =(D29-198)*0.78+G29 -> 1512.76 | K29: =+J29/I29 -> 0.67503793 | M29: 2390 | N29: 350 | O29: 90 | P29: 50 | Q29: =(90/4) -> 22.5 | R29: =+M29*0.02 -> 47.8 | S29: 20 | T29: 15 | U29: 10 | W29: =+M29 -> 2390 | X29: =+M29-SUM(N29:U29) -> 1784.7 | Y29: =+X29/W29 -> 0.7467364 | AA29: =+W29-I29 -> 149 | AB29: =+X29-J29 -> 271.94 | AD29: =+(W29-I29)/I29 -> 0.066488175 | AE29: =+(X29-J29)/J29 -> 0.17976414 | AG29: =+I29-SUM(N29:U29)-J29 -> 122.94 | AH29: =+(+I29-SUM(N29:U29)-J29)/J29 -> 0.081268674
B31: Total | D31: =+SUM(D11:D30) -> 65310 | E31: =+SUM(E11:E30) -> 3819 | F31: =+SUM(F11:F30) -> 950 | G31: =+SUM(G11:G30) -> 2185 | I31: =+SUM(I11:I30) -> 70079 | J31: =+SUM(J11:J30) -> 50192.44 | M31: =+SUM(M11:M30) -> 76930 | N31: =+SUM(N11:N30) -> 6650 | O31: =+SUM(O11:O30) -> 1710 | P31: =+SUM(P11:P30) -> 950 | Q31: =+SUM(Q11:Q30) -> 427.5 | R31: =+SUM(R11:R30) -> 1538.6 | S31: =+SUM(S11:S30) -> 380 | T31: =+SUM(T11:T30) -> 285 | U31: =+SUM(U11:U30) -> 190 | W31: =+SUM(W11:W30) -> 76930 | X31: =+SUM(X11:X30) -> 64798.9 | AA31: =+SUM(AA11:AA30) -> 6851 | AB31: =+SUM(AB11:AB30) -> 14606.46 | AG31: =+SUM(AG11:AG30) -> 7755.46 | AH31: =+(+I31-SUM(N31:U31)-J31)/J31 -> 0.1545145
A33: (1) : taux moyen Alp Agence calculé de 24,5% en 2025/26 sur l'ensemble des locations. Comprend les prestations annexes
A34: comme panier accueil...
A35: (2) : une prestation tous les 15 jours. Soit 90€/4 (90€ pour entrée ET sortie)
A36: (3) : considérée à 2% via Stripe. Permet de gérer la caution. 1,5% carte européenne, 2,5% britannique. 2% retenu en moyenne
A37: (4) : Garantie propriétaire étendue : 200€ / an estimée. Soit 15€ / semaine
A38: (5) : 2200€ / an lissé sur les 3 dernières années : soit 115€ / semaine
A39: (6) : Seuls 3 clients n'ont pas pris le ménage en 2025/26
A40: (7) : Via Swikly. Considée à 2%. Soit pour 1000€. Montant retenu correspond à une caution non utilisée
A41: (8) : Bois, produit douche, ménage, produit lave vaisselle

Sheet Questions Snow
A2: Règlements CESU : comment cela fonctionne ?
A3: 90€ arrivée ET départ
A4: Lits faits ? Non pas possible
A5: Panier de bienvenue
A6: Location draps : elle s'en occupe. Quel prix ?
A7: Qui paye les produits ménagers ?
A8: Est-ce qu'il y a la possibilité de commander des forfaits avec tarifs réduits ?
A10: Lits parapluie / chaise haute

Sheet A faire
A2: Assurance
A3: - propriétaire
A4: - locataire
A6: Ramonage
A8: Consuel pour électricité
A9: - 0970834833
A10: - Prix pour vérifier installation et/ou tableeau
A12: Tarifs chez un loueur de ski
